RyuzakiLib/__init__.py
RyuzakiLib/__version__.py
RyuzakiLib/_openai_scripts.py
RyuzakiLib/akenoai.py
RyuzakiLib/api_requestor.py
RyuzakiLib/bot.py
RyuzakiLib/channels.py
RyuzakiLib/cli.py
RyuzakiLib/custom_repo.py
RyuzakiLib/decorator.py
RyuzakiLib/embeddings_utils.py
RyuzakiLib/error.py
RyuzakiLib/fastapi.py
RyuzakiLib/functions_date.py
RyuzakiLib/mental.py
RyuzakiLib/object_classes.py
RyuzakiLib/openai_object.py
RyuzakiLib/openai_response.py
RyuzakiLib/pushdb.py
RyuzakiLib/pyrogramMod.py
RyuzakiLib/quote.py
RyuzakiLib/reminder.py
RyuzakiLib/story.py
RyuzakiLib/to_async.py
RyuzakiLib/tr.py
RyuzakiLib/upload_progress.py
RyuzakiLib/validators.py
RyuzakiLib/version_manager.py
RyuzakiLib/wandb_logger.py
RyuzakiLib/api/__init__.py
RyuzakiLib/api/fullstack.py
RyuzakiLib/api/jiosaavn.py
RyuzakiLib/api/private.py
RyuzakiLib/api/reqs.py
RyuzakiLib/api/yohasakura.py
RyuzakiLib/api/youtube.py
RyuzakiLib/client/__init__.py
RyuzakiLib/client/clients.py
RyuzakiLib/db/__init__.py
RyuzakiLib/db/pymongo.py
RyuzakiLib/dl/__init__.py
RyuzakiLib/dl/facebook.py
RyuzakiLib/dl/instagram.py
RyuzakiLib/dl/tools.py
RyuzakiLib/extreme/__init__.py
RyuzakiLib/extreme/dnsinfo.py
RyuzakiLib/extreme/quotestk.py
RyuzakiLib/extreme/userinfo.py
RyuzakiLib/extreme/webshot.py
RyuzakiLib/hackertools/__init__.py
RyuzakiLib/hackertools/alldownloader.py
RyuzakiLib/hackertools/blackbox.py
RyuzakiLib/hackertools/chatgpt.py
RyuzakiLib/hackertools/cloudflare.py
RyuzakiLib/hackertools/downloader.py
RyuzakiLib/hackertools/farfalle.py
RyuzakiLib/hackertools/flux.py
RyuzakiLib/hackertools/gemini.py
RyuzakiLib/hackertools/github.py
RyuzakiLib/hackertools/huggingface.py
RyuzakiLib/hackertools/ipinfo.py
RyuzakiLib/hackertools/ocrapi.py
RyuzakiLib/hackertools/openai_api.py
RyuzakiLib/hackertools/prefixes.py
RyuzakiLib/hackertools/rmbg.py
RyuzakiLib/hackertools/tiktok.py
RyuzakiLib/hackertools/xnxx.py
RyuzakiLib/handlers/__init__.py
RyuzakiLib/handlers/handlers_holder.py
RyuzakiLib/media_devices/__init__.py
RyuzakiLib-1.4.1.dist-info/LICENSE
RyuzakiLib-1.4.1.dist-info/METADATA
RyuzakiLib-1.4.1.dist-info/WHEEL
RyuzakiLib-1.4.1.dist-info/top_level.txt
RyuzakiLib-1.4.1.dist-info/RECORD
