Metadata-Version: 2.1
Name: RyuzakiLib
Version: 1.4.1
Summary: RyuzakiLib Python Wrapper For API etc
License: MIT
Project-URL: Source, https://github.com/TeamKillerX/RyuzakiLib/
Project-URL: Issues, https://github.com/TeamKillerX/RyuzakiLib/issues
Keywords: API,RyuzakiLib,Ryuzaki_Library,Ryuzaki-API
Classifier: Programming Language :: Python :: 3
Classifier: Programming Language :: Python :: 3.7
Classifier: Programming Language :: Python :: 3.8
Classifier: Programming Language :: Python :: 3.9
Classifier: Programming Language :: Python :: 3.10
Classifier: Programming Language :: Python :: 3.11
Classifier: Development Status :: 5 - Production/Stable
Classifier: License :: OSI Approved :: MIT License
Classifier: Operating System :: OS Independent
Classifier: Intended Audience :: Developers
Classifier: Natural Language :: English
Requires-Python: ~=3.7
License-File: LICENSE
Requires-Dist: requests
Provides-Extra: all
Requires-Dist: aiohttp ; extra == 'all'
Requires-Dist: aiofiles ; extra == 'all'
Requires-Dist: pyrogram ; extra == 'all'
Requires-Dist: bs4 ; extra == 'all'
Requires-Dist: google-search-results ; extra == 'all'
Requires-Dist: httpx[http2] ; extra == 'all'
Requires-Dist: Python-IO ; extra == 'all'
Requires-Dist: Pillow ; extra == 'all'
Requires-Dist: openai ; extra == 'all'
Requires-Dist: tqdm ; extra == 'all'
Requires-Dist: pre-commit ; extra == 'all'
Requires-Dist: gpytranslate ; extra == 'all'
Requires-Dist: Flask ; extra == 'all'
Requires-Dist: pymongo ; extra == 'all'
Requires-Dist: pytz ; extra == 'all'
Requires-Dist: urllib3 ; extra == 'all'
Requires-Dist: pydantic ; extra == 'all'
Requires-Dist: typing-extensions ; extra == 'all'
Requires-Dist: typing ; extra == 'all'
Requires-Dist: deprecation ; extra == 'all'
Requires-Dist: psutil ; extra == 'all'
Requires-Dist: screeninfo ; extra == 'all'
Requires-Dist: g4f ; extra == 'all'
Requires-Dist: curl-cffi ; extra == 'all'
Requires-Dist: google-generativeai ; extra == 'all'
Requires-Dist: huggingface-hub >=0.23.2 ; extra == 'all'
Requires-Dist: motor ; extra == 'all'
Requires-Dist: wget ; extra == 'all'
Requires-Dist: uvicorn[standard] ; extra == 'all'
Requires-Dist: fastapi[all] ; extra == 'all'
Requires-Dist: authlib ; extra == 'all'
Requires-Dist: python-dateutil ; extra == 'all'
Provides-Extra: porno
Requires-Dist: aiohttp ; extra == 'porno'
Requires-Dist: wget ; extra == 'porno'
Requires-Dist: requests ; extra == 'porno'
Requires-Dist: httpx[http2] ; extra == 'porno'
Provides-Extra: standard
Requires-Dist: g4f ; extra == 'standard'
Requires-Dist: httpx[http2] ; extra == 'standard'
Requires-Dist: typing ; extra == 'standard'
Requires-Dist: aiohttp ; extra == 'standard'
Requires-Dist: bs4 ; extra == 'standard'
Requires-Dist: openai ; extra == 'standard'
Requires-Dist: google-generativeai ; extra == 'standard'
Requires-Dist: curl-cffi ; extra == 'standard'
Requires-Dist: motor ; extra == 'standard'
Requires-Dist: typing-extensions ; extra == 'standard'
Requires-Dist: huggingface-hub >=0.23.2 ; extra == 'standard'
Requires-Dist: authlib ; extra == 'standard'
Requires-Dist: gpytranslate ; extra == 'standard'
Requires-Dist: fastapi[all] ; extra == 'standard'
Requires-Dist: uvicorn[standard] ; extra == 'standard'
Requires-Dist: pyrogram ; extra == 'standard'
